Workbook

Sheet 0_Index
A1: CAPSTONE_EXCEL_AGGREGATES.xlsx
A2: Source: outputs\part_d_co_clean.csv (390,473 rows, Colorado only). Group totals carried over from CAPSTONE_AGGREGATES.xlsx, verified PASS in VERIFICATION.md check 2. Per-unit metrics and all reconciliation values are live Excel formulas.
A4: Sheet | B4: Grouped by | C4: Groups (rows) | D4: Metrics
A5: Reconciliation | B5: -- | C5: 12 | D5: Tie-out of every tab to the cleaned dataset totals
A6: By_Prescriber | B6: Prscrbr_NPI | C6: 19390 | D6: Total drug cost, total claims, total 30-day fills, cost per claim, cost per 30-day fill, cumulative % of total cost
A7: By_Specialty | B7: Prscrbr_Type (specialty) | C7: 97 | D7: Total drug cost, total claims, total 30-day fills, cost per claim, cost per 30-day fill, cumulative % of total cost
A8: By_Generic_Drug | B8: Gnrc_Name | C8: 1177 | D8: Total drug cost, total claims, total 30-day fills, cost per claim, cost per 30-day fill, cumulative % of total cost

Sheet Reconciliation
A1: RECONCILIATION -- every aggregate tab tied back to outputs\part_d_co_clean.csv
A2: Expected values were computed once from the cleaned file (390,473 rows). Each aggregate tab is a complete partition of those rows, so each tab must reproduce every total exactly.
A4: Cleaned dataset -- reference totals
A5: Rows in cleaned file | B5: 390473
A6: Total drug cost ($) | B6: 2.7374554e+09
A7: Total claims | B7: 16573710
A8: Total 30-day fills | B8: 33119594
A9: Distinct prescribers (NPI) | B9: 19390
A10: Distinct specialties | B10: 97
A11: Distinct generic drugs | B11: 1177
A13: Tie-out checks
A14: # | B14: Check | C14: Tab | D14: Expected | E14: Workbook value (live formula) | F14: Delta | G14: Status
A15: 1 | B15: Total drug cost ($) | C15: By_Prescriber | D15: 2.7374554e+09 | E15: =By_Prescriber!F2 -> 2.7374554e+09 | F15: =ROUND(E15-D15,2) -> 0 | G15: =IF(F15=0,"TIE","CHECK") -> TIE
A16: 2 | B16: Total claims | C16: By_Prescriber | D16: 16573710 | E16: =By_Prescriber!G2 -> 16573710 | F16: =ROUND(E16-D16,0) -> 0 | G16: =IF(F16=0,"TIE","CHECK") -> TIE
A17: 3 | B17: Total 30-day fills | C17: By_Prescriber | D17: 33119594 | E17: =By_Prescriber!H2 -> 33119594 | F17: =ROUND(E17-D17,1) -> 0 | G17: =IF(F17=0,"TIE","CHECK") -> TIE
A18: 4 | B18: Group count (rows) | C18: By_Prescriber | D18: 19390 | E18: =COUNTA(By_Prescriber!A4:A19393) -> 19390 | F18: =ROUND(E18-D18,0) -> 0 | G18: =IF(F18=0,"TIE","CHECK") -> TIE
A19: 5 | B19: Total drug cost ($) | C19: By_Specialty | D19: 2.7374554e+09 | E19: =By_Specialty!B2 -> 2.7374554e+09 | F19: =ROUND(E19-D19,2) -> 0 | G19: =IF(F19=0,"TIE","CHECK") -> TIE
A20: 6 | B20: Total claims | C20: By_Specialty | D20: 16573710 | E20: =By_Specialty!C2 -> 16573710 | F20: =ROUND(E20-D20,0) -> 0 | G20: =IF(F20=0,"TIE","CHECK") -> TIE
A21: 7 | B21: Total 30-day fills | C21: By_Specialty | D21: 33119594 | E21: =By_Specialty!D2 -> 33119594 | F21: =ROUND(E21-D21,1) -> 0 | G21: =IF(F21=0,"TIE","CHECK") -> TIE
A22: 8 | B22: Group count (rows) | C22: By_Specialty | D22: 97 | E22: =COUNTA(By_Specialty!A4:A100) -> 97 | F22: =ROUND(E22-D22,0) -> 0 | G22: =IF(F22=0,"TIE","CHECK") -> TIE
A23: 9 | B23: Total drug cost ($) | C23: By_Generic_Drug | D23: 2.7374554e+09 | E23: =By_Generic_Drug!B2 -> 2.7374554e+09 | F23: =ROUND(E23-D23,2) -> 0 | G23: =IF(F23=0,"TIE","CHECK") -> TIE
A24: 10 | B24: Total claims | C24: By_Generic_Drug | D24: 16573710 | E24: =By_Generic_Drug!C2 -> 16573710 | F24: =ROUND(E24-D24,0) -> 0 | G24: =IF(F24=0,"TIE","CHECK") -> TIE
A25: 11 | B25: Total 30-day fills | C25: By_Generic_Drug | D25: 33119594 | E25: =By_Generic_Drug!D2 -> 33119594 | F25: =ROUND(E25-D25,1) -> 0 | G25: =IF(F25=0,"TIE","CHECK") -> TIE
A26: 12 | B26: Group count (rows) | C26: By_Generic_Drug | D26: 1177 | E26: =COUNTA(By_Generic_Drug!A4:A1180) -> 1177 | F26: =ROUND(E26-D26,0) -> 0 | G26: =IF(F26=0,"TIE","CHECK") -> TIE
A28: Note: source row count (390,473) is not summable from an aggregate tab -- each tab collapses those rows into groups. It is verified instead by the group counts above matching the distinct-entity counts of the cleaned file.

Sheet By_Prescriber
A1: Source: Medicare_Part_D_Prescribers_by_Provider_and_Drug_2024.csv | Rows in source: 390,473 | Filter: None -- source file is pre-filtered to Colorado (Prscrbr_State_Abrvtn = 'CO') | Rolled up by: Prscrbr_NPI | Groups: 19,390
A2: GRAND TOTAL (SUM of the column below) | F2: =SUM(F4:F19393) -> 2.7374554e+09 | G2: =SUM(G4:G19393) -> 16573710 | H2: =SUM(H4:H19393) -> 33119594
A3: Prscrbr_NPI | B3: Last/Org Name | C3: First Name | D3: City (Prscrbr_City) | E3: Specialty (Prscrbr_Type) | F3: Total Drug Cost | G3: Total Claims | H3: Total 30-Day Fills | I3: Prescriber Count | J3: Cost per Claim | K3: Cost per 30-Day Fill | L3: Cumulative % of Total Cost
A4: 1801871215 | B4: Burke | C4: John | D4: Aurora | E4: Hematology-Oncology | F4: 16360898 | G4: 1901 | H4: 2482.8 | I4: 1 | J4: =IFERROR(F4/G4,"") -> 8606.4694 | K4: =IFERROR(F4/H4,"") -> 6589.6965 | L4: =F4/$F$2*100 -> 0.59766813
A5: 1457414203 | B5: George | C5: Marjorie | D5: Denver | E5: Critical Care (Intensivists) | F5: 13244806 | G5: 2066 | H5: 2818.9 | I5: 1 | J5: =IFERROR(F5/G5,"") -> 6410.8452 | K5: =IFERROR(F5/H5,"") -> 4698.5725 | L5: =L4+F5/$F$2*100 -> 1.0815045
A6: 1245678648 | B6: Howe | C6: Laura | D6: Greeley | E6: Rheumatology | F6: 12469453 | G6: 5273 | H6: 10256 | I6: 1 | J6: =IFERROR(F6/G6,"") -> 2364.774 | K6: =IFERROR(F6/H6,"") -> 1215.8203 | L6: =L5+F6/$F$2*100 -> 1.5370171
A7: 1700975042 | B7: Ambardekar | C7: Amrut | D7: Aurora | E7: Advanced Heart Failure and Transplant Cardiology | F7: 11374976 | G7: 1861 | H7: 4267.8 | I7: 1 | J7: =IFERROR(F7/G7,"") -> 6112.2922 | K7: =IFERROR(F7/H7,"") -> 2665.302 | L7: =L6+F7/$F$2*100 -> 1.9525481
A8: 1255667655 | B8: Benton | C8: Christopher | D8: Englewood | E8: Medical Oncology | F8: 11133184 | G8: 1655 | H8: 2221.6 | I8: 1 | J8: =IFERROR(F8/G8,"") -> 6726.9997 | K8: =IFERROR(F8/H8,"") -> 5011.3362 | L8: =L7+F8/$F$2*100 -> 2.3592464
A9: 1417047192 | B9: Nick | C9: Jerry | D9: Denver | E9: Pulmonary Disease | F9: 10658319 | G9: 951 | H9: 1070.5 | I9: 1 | J9: =IFERROR(F9/G9,"") -> 11207.486 | K9: =IFERROR(F9/H9,"") -> 9956.3937 | L9: =L8+F9/$F$2*100 -> 2.7485978
A10: 1962523555 | B10: Melendez | C10: Elisa | D10: Thornton | E10: Family Practice | F10: 10559186 | G10: 66015 | H10: 75293.1 | I10: 1 | J10: =IFERROR(F10/G10,"") -> 159.95131 | K10: =IFERROR(F10/H10,"") -> 140.24108 | L10: =L9+F10/$F$2*100 -> 3.1343277
A11: 1861455099 | B11: Timms | C11: Patrick | D11: Pueblo | E11: Rheumatology | F11: 10464865 | G11: 8475 | H11: 12719.9 | I11: 1 | J11: =IFERROR(F11/G11,"") -> 1234.7923 | K11: =IFERROR(F11/H11,"") -> 822.71599 | L11: =L10+F11/$F$2*100 -> 3.5166121
A12: 1760402655 | B12: Dauber | C12: Ira | D12: Littleton | E12: Interventional Cardiology | F12: 9676267.8 | G12: 9128 | H12: 22458.5 | I12: 1 | J12: =IFERROR(F12/G12,"") -> 1060.0644 | K12: =IFERROR(F12/H12,"") -> 430.85103 | L12: =L11+F12/$F$2*100 -> 3.8700889
A13: 1932299518 | B13: Saavedra | C13: Milene | D13: Denver | E13: Critical Care (Intensivists) | F13: 9660656.8 | G13: 1090 | H13: 1204.7 | I13: 1 | J13: =IFERROR(F13/G13,"") -> 8862.9879 | K13: =IFERROR(F13/H13,"") -> 8019.1391 | L13: =L12+F13/$F$2*100 -> 4.2229953
A14: 1114064490 | B14: Dong | C14: Lin-Wang | D14: Greeley | E14: Cardiology | F14: 8607685.2 | G14: 5418 | H14: 11027.5 | I14: 1 | J14: =IFERROR(F14/G14,"") -> 1588.72 | K14: =IFERROR(F14/H14,"") -> 780.56542 | L14: =L13+F14/$F$2*100 -> 4.5374364
A15: 1417903154 | B15: Moore | C15: James | D15: Fort Collins | E15: Hematology-Oncology | F15: 8374555.3 | G15: 1918 | H15: 2570.7 | I15: 1 | J15: =IFERROR(F15/G15,"") -> 4366.2958 | K15: =IFERROR(F15/H15,"") -> 3257.6945 | L15: =L14+F15/$F$2*100 -> 4.8433613
A16: 1760799894 | B16: Chavda | C16: Rupal | D16: Pueblo | E16: Rheumatology | F16: 7829842.2 | G16: 6042 | H16: 12040.4 | I16: 1 | J16: =IFERROR(F16/G16,"") -> 1295.9024 | K16: =IFERROR(F16/H16,"") -> 650.29752 | L16: =L15+F16/$F$2*100 -> 5.1293876
... A19393: 1235899568 | B19393: Hofmeister | C19393: Annemarie | D19393: Timnath | E19393: Nurse Practitioner | F19393: 0 | G19393: 11 | H19393: 11 | I19393: 1 | J19393: =IFERROR(F19393/G19393,"") -> 0 | K19393: =IFERROR(F19393/H19393,"") -> 0 | L19393: =L19392+F19393/$F$2*100 -> 100

Sheet By_Specialty
A1: Source: Medicare_Part_D_Prescribers_by_Provider_and_Drug_2024.csv | Rows in source: 390,473 | Filter: None -- source file is pre-filtered to Colorado (Prscrbr_State_Abrvtn = 'CO') | Rolled up by: Prscrbr_Type | Groups: 97
A2: GRAND TOTAL (SUM of the column below) | B2: =SUM(B4:B100) -> 2.7374554e+09 | C2: =SUM(C4:C100) -> 16573710 | D2: =SUM(D4:D100) -> 33119594
A3: Specialty (Prscrbr_Type) | B3: Total Drug Cost | C3: Total Claims | D3: Total 30-Day Fills | E3: Prescriber Count | F3: Cost per Claim | G3: Cost per 30-Day Fill | H3: Cumulative % of Total Cost
A4: Nurse Practitioner | B4: 3.9283006e+08 | C4: 2869709 | D4: 4905637.9 | E4: 3509 | F4: =IFERROR(B4/C4,"") -> 136.88846 | G4: =IFERROR(B4/D4,"") -> 80.077263 | H4: =B4/$B$2*100 -> 14.35019
A5: Family Practice | B5: 3.5218033e+08 | C5: 4834922 | D5: 10657930 | E5: 2288 | F5: =IFERROR(B5/C5,"") -> 72.840954 | G5: =IFERROR(B5/D5,"") -> 33.04397 | H5: =H4+B5/$B$2*100 -> 27.215435
A6: Internal Medicine | B6: 3.1576383e+08 | C6: 3222260 | D6: 7231861.2 | E6: 1292 | F6: =IFERROR(B6/C6,"") -> 97.994523 | G6: =IFERROR(B6/D6,"") -> 43.662872 | H6: =H5+B6/$B$2*100 -> 38.750374
A7: Physician Assistant | B7: 2.5635452e+08 | C7: 1744525 | D7: 3208302.5 | E7: 3010 | F7: =IFERROR(B7/C7,"") -> 146.94803 | G7: =IFERROR(B7/D7,"") -> 79.903476 | H7: =H6+B7/$B$2*100 -> 48.115076
A8: Hematology-Oncology | B8: 2.2778835e+08 | C8: 85900 | D8: 132929.9 | E8: 115 | F8: =IFERROR(B8/C8,"") -> 2651.7852 | G8: =IFERROR(B8/D8,"") -> 1713.5975 | H8: =H7+B8/$B$2*100 -> 56.436247
A9: Cardiology | B9: 1.3489437e+08 | C9: 495701 | D9: 1290459.1 | E9: 205 | F9: =IFERROR(B9/C9,"") -> 272.12851 | G9: =IFERROR(B9/D9,"") -> 104.53208 | H9: =H8+B9/$B$2*100 -> 61.363976
A10: Rheumatology | B10: 1.3299365e+08 | C10: 146726 | D10: 284750.6 | E10: 89 | F10: =IFERROR(B10/C10,"") -> 906.40823 | G10: =IFERROR(B10/D10,"") -> 467.05311 | H10: =H9+B10/$B$2*100 -> 66.222271
A11: Pulmonary Disease | B11: 1.032829e+08 | C11: 113868 | D11: 177792.8 | E11: 154 | F11: =IFERROR(B11/C11,"") -> 907.04062 | G11: =IFERROR(B11/D11,"") -> 580.91723 | H11: =H10+B11/$B$2*100 -> 69.995223
A12: Neurology | B12: 98212591 | C12: 219462 | D12: 416706.2 | E12: 212 | F12: =IFERROR(B12/C12,"") -> 447.51525 | G12: =IFERROR(B12/D12,"") -> 235.68786 | H12: =H11+B12/$B$2*100 -> 73.582956
A13: Medical Oncology | B13: 85517730 | C13: 34964 | D13: 56961 | E13: 76 | F13: =IFERROR(B13/C13,"") -> 2445.8795 | G13: =IFERROR(B13/D13,"") -> 1501.3383 | H13: =H12+B13/$B$2*100 -> 76.706943
A14: Endocrinology | B14: 68725921 | C14: 139604 | D14: 325574.5 | E14: 94 | F14: =IFERROR(B14/C14,"") -> 492.29192 | G14: =IFERROR(B14/D14,"") -> 211.09123 | H14: =H13+B14/$B$2*100 -> 79.217519
A15: Critical Care (Intensivists) | B15: 59328932 | C15: 39790 | D15: 64982.2 | E15: 75 | F15: =IFERROR(B15/C15,"") -> 1491.0513 | G15: =IFERROR(B15/D15,"") -> 913.00283 | H15: =H14+B15/$B$2*100 -> 81.384822
A16: Urology | B16: 50352534 | C16: 157355 | D16: 324321.9 | E16: 178 | F16: =IFERROR(B16/C16,"") -> 319.99323 | G16: =IFERROR(B16/D16,"") -> 155.25481 | H16: =H15+B16/$B$2*100 -> 83.224214
... A100: Neuromusculoskeletal Medicine, Sports Medicine | B100: 185.62 | C100: 29 | D100: 29 | E100: 1 | F100: =IFERROR(B100/C100,"") -> 6.4006897 | G100: =IFERROR(B100/D100,"") -> 6.4006897 | H100: =H99+B100/$B$2*100 -> 100

Sheet By_Generic_Drug
A1: Source: Medicare_Part_D_Prescribers_by_Provider_and_Drug_2024.csv | Rows in source: 390,473 | Filter: None -- source file is pre-filtered to Colorado (Prscrbr_State_Abrvtn = 'CO') | Rolled up by: Gnrc_Name | Groups: 1,177
A2: GRAND TOTAL (SUM of the column below) | B2: =SUM(B4:B1180) -> 2.7374554e+09 | C2: =SUM(C4:C1180) -> 16573710 | D2: =SUM(D4:D1180) -> 33119594
A3: Generic Drug (Gnrc_Name) | B3: Total Drug Cost | C3: Total Claims | D3: Total 30-Day Fills | E3: Prescriber Count | F3: Cost per Claim | G3: Cost per 30-Day Fill | H3: Cumulative % of Total Cost
A4: Apixaban | B4: 2.441967e+08 | C4: 251325 | D4: 447173.5 | E4: 3970 | F4: =IFERROR(B4/C4,"") -> 971.63711 | G4: =IFERROR(B4/D4,"") -> 546.08937 | H4: =B4/$B$2*100 -> 8.9205726
A5: Semaglutide | B5: 1.1727331e+08 | C5: 93812 | D5: 130936.3 | E5: 2521 | F5: =IFERROR(B5/C5,"") -> 1250.0886 | G5: =IFERROR(B5/D5,"") -> 895.6516 | H5: =H4+B5/$B$2*100 -> 13.204599
A6: Empagliflozin | B6: 1.1269071e+08 | C6: 111517 | D6: 235451.8 | E6: 2922 | F6: =IFERROR(B6/C6,"") -> 1010.5249 | G6: =IFERROR(B6/D6,"") -> 478.61476 | H6: =H5+B6/$B$2*100 -> 17.321221
A7: Lenalidomide | B7: 92447409 | C7: 5814 | D7: 5818.7 | E7: 123 | F7: =IFERROR(B7/C7,"") -> 15900.827 | G7: =IFERROR(B7/D7,"") -> 15887.983 | H7: =H6+B7/$B$2*100 -> 20.698351
A8: Rivaroxaban | B8: 75261499 | C8: 75419 | D8: 143472.3 | E8: 2278 | F8: =IFERROR(B8/C8,"") -> 997.91166 | G8: =IFERROR(B8/D8,"") -> 524.57164 | H8: =H7+B8/$B$2*100 -> 23.447674
A9: Dulaglutide | B9: 64168615 | C9: 50205 | D9: 67525.2 | E9: 1637 | F9: =IFERROR(B9/C9,"") -> 1278.132 | G9: =IFERROR(B9/D9,"") -> 950.29138 | H9: =H8+B9/$B$2*100 -> 25.791771
A10: Tirzepatide | B10: 63335484 | C10: 49215 | D10: 60049.6 | E10: 1296 | F10: =IFERROR(B10/C10,"") -> 1286.9142 | G10: =IFERROR(B10/D10,"") -> 1054.7195 | H10: =H9+B10/$B$2*100 -> 28.105434
A11: Adalimumab | B11: 62895534 | C11: 7410 | D11: 7749.2 | E11: 209 | F11: =IFERROR(B11/C11,"") -> 8487.9263 | G11: =IFERROR(B11/D11,"") -> 8116.3906 | H11: =H10+B11/$B$2*100 -> 30.403025
A12: Fluticasone/Umeclidin/Vilanter | B12: 45187886 | C12: 49441 | D12: 71063.1 | E12: 1143 | F12: =IFERROR(B12/C12,"") -> 913.97597 | G12: =IFERROR(B12/D12,"") -> 635.88397 | H12: =H11+B12/$B$2*100 -> 32.053751
A13: Etanercept | B13: 40348532 | C13: 5553 | D13: 5873.4 | E13: 103 | F13: =IFERROR(B13/C13,"") -> 7266.0781 | G13: =IFERROR(B13/D13,"") -> 6869.7061 | H13: =H12+B13/$B$2*100 -> 33.527694
A14: Tafamidis | B14: 39818740 | C14: 1633 | D14: 1714 | E14: 45 | F14: =IFERROR(B14/C14,"") -> 24383.797 | G14: =IFERROR(B14/D14,"") -> 23231.47 | H14: =H13+B14/$B$2*100 -> 34.982284
A15: Bictegrav/Emtricit/Tenofov Ala | B15: 35459892 | C15: 8413 | D15: 9374.1 | E15: 116 | F15: =IFERROR(B15/C15,"") -> 4214.8927 | G15: =IFERROR(B15/D15,"") -> 3782.7516 | H15: =H14+B15/$B$2*100 -> 36.277643
A16: Dupilumab | B16: 33517915 | C16: 8445 | D16: 8707.2 | E16: 299 | F16: =IFERROR(B16/C16,"") -> 3968.9657 | G16: =IFERROR(B16/D16,"") -> 3849.4482 | H16: =H15+B16/$B$2*100 -> 37.502062
... A1180: Isoniazid | B1180: 86.15 | C1180: 27 | D1180: 27 | E1180: 2 | F1180: =IFERROR(B1180/C1180,"") -> 3.1907407 | G1180: =IFERROR(B1180/D1180,"") -> 3.1907407 | H1180: =H1179+B1180/$B$2*100 -> 100
